{"code":1,"list":[{"name":"邵磊","id":3,"sex":"女","age":"45","tel":"17718919371","msg":"已通知","ps":"-","date":"2017-11-10"},{"name":"曹明","id":1,"sex":"女","age":"63","tel":"13135613285","msg":"已通知","ps":"本周二参加活动","date":"2017-11-10"},{"name":"曹明","id":1,"sex":"女","age":"63","tel":"13135613285","msg":"已通知","ps":"本周二参加活动","date":"2017-11-10"},{"id":0,"name":"张三","tel":135623019562,"date":"2017-06-01","msg":"-"},{"id":1,"name":"李四","tel":"18203623892","date":"2017-11-08","msg":"-"},{"id":2,"name":"王五","tel":"18203623892","date":"2017-11-09","msg":"-"}]}